<Ui xmlns="http://www.blizzard.com/wow/ui/" xmlns:xsi="http://www.w3.org/2001/XMLSchema-instance" xsi:schemaLocation="http://www.blizzard.com/wow/ui/ C:\Projects\WoW\Bin\Interface\FrameXML\UI.xsd">
	<Script file="localization.lua"/> 
	<Script file="CooldownCountInsomniax_BibToolbars.lua"/> 
	
	<Frame name="CooldownCountInsomniax_BibToolbarsFrame" frameStrata="LOW" enableMouse="false" parent="UIParent" hidden="false">
		<Scripts>
			<OnLoad>
				CooldownCountInsomniax_BibToolbars_OnLoad();
			</OnLoad>
		</Scripts>
	</Frame>
	<Frame name="BibActionButton1CooldownCountFrame" parent="BibActionButton1" hidden="true">
        <Size>
            <AbsDimension x="32" y="32"/>
        </Size>
        <Anchors>
            <Anchor point="CENTER" relativeTo="$parent" relativePoint="CENTER">
                <Offset>
                    <AbsDimension x="0" y="0"/>
                </Offset>
            </Anchor>
        </Anchors>
		<Layers>
			<Layer level="ARTWORK">
				<FontString name="BibActionButton1CooldownCount" inherits="GameFontNormalLarge" hidden="true" justifyH="CENTER">
					<Anchors>
						<Anchor point="CENTER">
							<Offset>
								<AbsDimension x="0" y="0"/>
							</Offset>
						</Anchor>
					</Anchors>
				</FontString>
			</Layer>
		</Layers>
	</Frame>
	<Frame name="BibActionButton2CooldownCountFrame" parent="BibActionButton2" hidden="true">
        <Size>
            <AbsDimension x="32" y="32"/>
        </Size>
        <Anchors>
            <Anchor point="CENTER" relativeTo="$parent" relativePoint="CENTER">
                <Offset>
                    <AbsDimension x="0" y="0"/>
                </Offset>
            </Anchor>
        </Anchors>
		<Layers>
			<Layer level="ARTWORK">
				<FontString name="BibActionButton2CooldownCount" inherits="GameFontNormalLarge" hidden="true" justifyH="CENTER">
					<Anchors>
						<Anchor point="CENTER">
							<Offset>
								<AbsDimension x="0" y="0"/>
							</Offset>
						</Anchor>
					</Anchors>
				</FontString>
			</Layer>
		</Layers>
	</Frame>
	<Frame name="BibActionButton3CooldownCountFrame" parent="BibActionButton3" hidden="true">
        <Size>
            <AbsDimension x="32" y="32"/>
        </Size>
        <Anchors>
            <Anchor point="CENTER" relativeTo="$parent" relativePoint="CENTER">
                <Offset>
                    <AbsDimension x="0" y="0"/>
                </Offset>
            </Anchor>
        </Anchors>
		<Layers>
			<Layer level="ARTWORK">
				<FontString name="BibActionButton3CooldownCount" inherits="GameFontNormalLarge" hidden="true" justifyH="CENTER">
					<Anchors>
						<Anchor point="CENTER">
							<Offset>
								<AbsDimension x="0" y="0"/>
							</Offset>
						</Anchor>
					</Anchors>
				</FontString>
			</Layer>
		</Layers>
	</Frame>
	<Frame name="BibActionButton4CooldownCountFrame" parent="BibActionButton4" hidden="true">
        <Size>
            <AbsDimension x="32" y="32"/>
        </Size>
        <Anchors>
            <Anchor point="CENTER" relativeTo="$parent" relativePoint="CENTER">
                <Offset>
                    <AbsDimension x="0" y="0"/>
                </Offset>
            </Anchor>
        </Anchors>
		<Layers>
			<Layer level="ARTWORK">
				<FontString name="BibActionButton4CooldownCount" inherits="GameFontNormalLarge" hidden="true" justifyH="CENTER">
					<Anchors>
						<Anchor point="CENTER">
							<Offset>
								<AbsDimension x="0" y="0"/>
							</Offset>
						</Anchor>
					</Anchors>
				</FontString>
			</Layer>
		</Layers>
	</Frame>
	<Frame name="BibActionButton5CooldownCountFrame" parent="BibActionButton5" hidden="true">
        <Size>
            <AbsDimension x="32" y="32"/>
        </Size>
        <Anchors>
            <Anchor point="CENTER" relativeTo="$parent" relativePoint="CENTER">
                <Offset>
                    <AbsDimension x="0" y="0"/>
                </Offset>
            </Anchor>
        </Anchors>
		<Layers>
			<Layer level="ARTWORK">
				<FontString name="BibActionButton5CooldownCount" inherits="GameFontNormalLarge" hidden="true" justifyH="CENTER">
					<Anchors>
						<Anchor point="CENTER">
							<Offset>
								<AbsDimension x="0" y="0"/>
							</Offset>
						</Anchor>
					</Anchors>
				</FontString>
			</Layer>
		</Layers>
	</Frame>
	<Frame name="BibActionButton6CooldownCountFrame" parent="BibActionButton6" hidden="true">
        <Size>
            <AbsDimension x="32" y="32"/>
        </Size>
        <Anchors>
            <Anchor point="CENTER" relativeTo="$parent" relativePoint="CENTER">
                <Offset>
                    <AbsDimension x="0" y="0"/>
                </Offset>
            </Anchor>
        </Anchors>
		<Layers>
			<Layer level="ARTWORK">
				<FontString name="BibActionButton6CooldownCount" inherits="GameFontNormalLarge" hidden="true" justifyH="CENTER">
					<Anchors>
						<Anchor point="CENTER">
							<Offset>
								<AbsDimension x="0" y="0"/>
							</Offset>
						</Anchor>
					</Anchors>
				</FontString>
			</Layer>
		</Layers>
	</Frame>
	<Frame name="BibActionButton7CooldownCountFrame" parent="BibActionButton7" hidden="true">
        <Size>
            <AbsDimension x="32" y="32"/>
        </Size>
        <Anchors>
            <Anchor point="CENTER" relativeTo="$parent" relativePoint="CENTER">
                <Offset>
                    <AbsDimension x="0" y="0"/>
                </Offset>
            </Anchor>
        </Anchors>
		<Layers>
			<Layer level="ARTWORK">
				<FontString name="BibActionButton7CooldownCount" inherits="GameFontNormalLarge" hidden="true" justifyH="CENTER">
					<Anchors>
						<Anchor point="CENTER">
							<Offset>
								<AbsDimension x="0" y="0"/>
							</Offset>
						</Anchor>
					</Anchors>
				</FontString>
			</Layer>
		</Layers>
	</Frame>
	<Frame name="BibActionButton8CooldownCountFrame" parent="BibActionButton8" hidden="true">
        <Size>
            <AbsDimension x="32" y="32"/>
        </Size>
        <Anchors>
            <Anchor point="CENTER" relativeTo="$parent" relativePoint="CENTER">
                <Offset>
                    <AbsDimension x="0" y="0"/>
                </Offset>
            </Anchor>
        </Anchors>
		<Layers>
			<Layer level="ARTWORK">
				<FontString name="BibActionButton8CooldownCount" inherits="GameFontNormalLarge" hidden="true" justifyH="CENTER">
					<Anchors>
						<Anchor point="CENTER">
							<Offset>
								<AbsDimension x="0" y="0"/>
							</Offset>
						</Anchor>
					</Anchors>
				</FontString>
			</Layer>
		</Layers>
	</Frame>
	<Frame name="BibActionButton9CooldownCountFrame" parent="BibActionButton9" hidden="true">
        <Size>
            <AbsDimension x="32" y="32"/>
        </Size>
        <Anchors>
            <Anchor point="CENTER" relativeTo="$parent" relativePoint="CENTER">
                <Offset>
                    <AbsDimension x="0" y="0"/>
                </Offset>
            </Anchor>
        </Anchors>
		<Layers>
			<Layer level="ARTWORK">
				<FontString name="BibActionButton9CooldownCount" inherits="GameFontNormalLarge" hidden="true" justifyH="CENTER">
					<Anchors>
						<Anchor point="CENTER">
							<Offset>
								<AbsDimension x="0" y="0"/>
							</Offset>
						</Anchor>
					</Anchors>
				</FontString>
			</Layer>
		</Layers>
	</Frame>

	<Frame name="BibActionButton10CooldownCountFrame" parent="BibActionButton10" hidden="true">
        <Size>
            <AbsDimension x="32" y="32"/>
        </Size>
        <Anchors>
            <Anchor point="CENTER" relativeTo="$parent" relativePoint="CENTER">
                <Offset>
                    <AbsDimension x="0" y="0"/>
                </Offset>
            </Anchor>
        </Anchors>
		<Layers>
			<Layer level="ARTWORK">
				<FontString name="BibActionButton10CooldownCount" inherits="GameFontNormalLarge" hidden="true" justifyH="CENTER">
					<Anchors>
						<Anchor point="CENTER">
							<Offset>
								<AbsDimension x="0" y="0"/>
							</Offset>
						</Anchor>
					</Anchors>
				</FontString>
			</Layer>
		</Layers>
	</Frame>
	<Frame name="BibActionButton11CooldownCountFrame" parent="BibActionButton11" hidden="true">
        <Size>
            <AbsDimension x="32" y="32"/>
        </Size>
        <Anchors>
            <Anchor point="CENTER" relativeTo="$parent" relativePoint="CENTER">
                <Offset>
                    <AbsDimension x="0" y="0"/>
                </Offset>
            </Anchor>
        </Anchors>
		<Layers>
			<Layer level="ARTWORK">
				<FontString name="BibActionButton11CooldownCount" inherits="GameFontNormalLarge" hidden="true" justifyH="CENTER">
					<Anchors>
						<Anchor point="CENTER">
							<Offset>
								<AbsDimension x="0" y="0"/>
							</Offset>
						</Anchor>
					</Anchors>
				</FontString>
			</Layer>
		</Layers>
	</Frame>
	<Frame name="BibActionButton12CooldownCountFrame" parent="BibActionButton12" hidden="true">
        <Size>
            <AbsDimension x="32" y="32"/>
        </Size>
        <Anchors>
            <Anchor point="CENTER" relativeTo="$parent" relativePoint="CENTER">
                <Offset>
                    <AbsDimension x="0" y="0"/>
                </Offset>
            </Anchor>
        </Anchors>
		<Layers>
			<Layer level="ARTWORK">
				<FontString name="BibActionButton12CooldownCount" inherits="GameFontNormalLarge" hidden="true" justifyH="CENTER">
					<Anchors>
						<Anchor point="CENTER">
							<Offset>
								<AbsDimension x="0" y="0"/>
							</Offset>
						</Anchor>
					</Anchors>
				</FontString>
			</Layer>
		</Layers>
	</Frame>
	<Frame name="BibActionButton13CooldownCountFrame" parent="BibActionButton13" hidden="true">
        <Size>
            <AbsDimension x="32" y="32"/>
        </Size>
        <Anchors>
            <Anchor point="CENTER" relativeTo="$parent" relativePoint="CENTER">
                <Offset>
                    <AbsDimension x="0" y="0"/>
                </Offset>
            </Anchor>
        </Anchors>
		<Layers>
			<Layer level="ARTWORK">
				<FontString name="BibActionButton13CooldownCount" inherits="GameFontNormalLarge" hidden="true" justifyH="CENTER">
					<Anchors>
						<Anchor point="CENTER">
							<Offset>
								<AbsDimension x="0" y="0"/>
							</Offset>
						</Anchor>
					</Anchors>
				</FontString>
			</Layer>
		</Layers>
	</Frame>
	<Frame name="BibActionButton14CooldownCountFrame" parent="BibActionButton14" hidden="true">
        <Size>
            <AbsDimension x="32" y="32"/>
        </Size>
        <Anchors>
            <Anchor point="CENTER" relativeTo="$parent" relativePoint="CENTER">
                <Offset>
                    <AbsDimension x="0" y="0"/>
                </Offset>
            </Anchor>
        </Anchors>
		<Layers>
			<Layer level="ARTWORK">
				<FontString name="BibActionButton14CooldownCount" inherits="GameFontNormalLarge" hidden="true" justifyH="CENTER">
					<Anchors>
						<Anchor point="CENTER">
							<Offset>
								<AbsDimension x="0" y="0"/>
							</Offset>
						</Anchor>
					</Anchors>
				</FontString>
			</Layer>
		</Layers>
	</Frame>
	<Frame name="BibActionButton15CooldownCountFrame" parent="BibActionButton15" hidden="true">
        <Size>
            <AbsDimension x="32" y="32"/>
        </Size>
        <Anchors>
            <Anchor point="CENTER" relativeTo="$parent" relativePoint="CENTER">
                <Offset>
                    <AbsDimension x="0" y="0"/>
                </Offset>
            </Anchor>
        </Anchors>
		<Layers>
			<Layer level="ARTWORK">
				<FontString name="BibActionButton15CooldownCount" inherits="GameFontNormalLarge" hidden="true" justifyH="CENTER">
					<Anchors>
						<Anchor point="CENTER">
							<Offset>
								<AbsDimension x="0" y="0"/>
							</Offset>
						</Anchor>
					</Anchors>
				</FontString>
			</Layer>
		</Layers>
	</Frame>
	<Frame name="BibActionButton16CooldownCountFrame" parent="BibActionButton16" hidden="true">
        <Size>
            <AbsDimension x="32" y="32"/>
        </Size>
        <Anchors>
            <Anchor point="CENTER" relativeTo="$parent" relativePoint="CENTER">
                <Offset>
                    <AbsDimension x="0" y="0"/>
                </Offset>
            </Anchor>
        </Anchors>
		<Layers>
			<Layer level="ARTWORK">
				<FontString name="BibActionButton16CooldownCount" inherits="GameFontNormalLarge" hidden="true" justifyH="CENTER">
					<Anchors>
						<Anchor point="CENTER">
							<Offset>
								<AbsDimension x="0" y="0"/>
							</Offset>
						</Anchor>
					</Anchors>
				</FontString>
			</Layer>
		</Layers>
	</Frame>
	<Frame name="BibActionButton17CooldownCountFrame" parent="BibActionButton17" hidden="true">
        <Size>
            <AbsDimension x="32" y="32"/>
        </Size>
        <Anchors>
            <Anchor point="CENTER" relativeTo="$parent" relativePoint="CENTER">
                <Offset>
                    <AbsDimension x="0" y="0"/>
                </Offset>
            </Anchor>
        </Anchors>
		<Layers>
			<Layer level="ARTWORK">
				<FontString name="BibActionButton17CooldownCount" inherits="GameFontNormalLarge" hidden="true" justifyH="CENTER">
					<Anchors>
						<Anchor point="CENTER">
							<Offset>
								<AbsDimension x="0" y="0"/>
							</Offset>
						</Anchor>
					</Anchors>
				</FontString>
			</Layer>
		</Layers>
	</Frame>
	<Frame name="BibActionButton18CooldownCountFrame" parent="BibActionButton18" hidden="true">
        <Size>
            <AbsDimension x="32" y="32"/>
        </Size>
        <Anchors>
            <Anchor point="CENTER" relativeTo="$parent" relativePoint="CENTER">
                <Offset>
                    <AbsDimension x="0" y="0"/>
                </Offset>
            </Anchor>
        </Anchors>
		<Layers>
			<Layer level="ARTWORK">
				<FontString name="BibActionButton18CooldownCount" inherits="GameFontNormalLarge" hidden="true" justifyH="CENTER">
					<Anchors>
						<Anchor point="CENTER">
							<Offset>
								<AbsDimension x="0" y="0"/>
							</Offset>
						</Anchor>
					</Anchors>
				</FontString>
			</Layer>
		</Layers>
	</Frame>
	<Frame name="BibActionButton19CooldownCountFrame" parent="BibActionButton19" hidden="true">
        <Size>
            <AbsDimension x="32" y="32"/>
        </Size>
        <Anchors>
            <Anchor point="CENTER" relativeTo="$parent" relativePoint="CENTER">
                <Offset>
                    <AbsDimension x="0" y="0"/>
                </Offset>
            </Anchor>
        </Anchors>
		<Layers>
			<Layer level="ARTWORK">
				<FontString name="BibActionButton19CooldownCount" inherits="GameFontNormalLarge" hidden="true" justifyH="CENTER">
					<Anchors>
						<Anchor point="CENTER">
							<Offset>
								<AbsDimension x="0" y="0"/>
							</Offset>
						</Anchor>
					</Anchors>
				</FontString>
			</Layer>
		</Layers>
	</Frame>

	<Frame name="BibActionButton20CooldownCountFrame" parent="BibActionButton20" hidden="true">
        <Size>
            <AbsDimension x="32" y="32"/>
        </Size>
        <Anchors>
            <Anchor point="CENTER" relativeTo="$parent" relativePoint="CENTER">
                <Offset>
                    <AbsDimension x="0" y="0"/>
                </Offset>
            </Anchor>
        </Anchors>
		<Layers>
			<Layer level="ARTWORK">
				<FontString name="BibActionButton20CooldownCount" inherits="GameFontNormalLarge" hidden="true" justifyH="CENTER">
					<Anchors>
						<Anchor point="CENTER">
							<Offset>
								<AbsDimension x="0" y="0"/>
							</Offset>
						</Anchor>
					</Anchors>
				</FontString>
			</Layer>
		</Layers>
	</Frame>
	<Frame name="BibActionButton21CooldownCountFrame" parent="BibActionButton21" hidden="true">
        <Size>
            <AbsDimension x="32" y="32"/>
        </Size>
        <Anchors>
            <Anchor point="CENTER" relativeTo="$parent" relativePoint="CENTER">
                <Offset>
                    <AbsDimension x="0" y="0"/>
                </Offset>
            </Anchor>
        </Anchors>
		<Layers>
			<Layer level="ARTWORK">
				<FontString name="BibActionButton21CooldownCount" inherits="GameFontNormalLarge" hidden="true" justifyH="CENTER">
					<Anchors>
						<Anchor point="CENTER">
							<Offset>
								<AbsDimension x="0" y="0"/>
							</Offset>
						</Anchor>
					</Anchors>
				</FontString>
			</Layer>
		</Layers>
	</Frame>
	<Frame name="BibActionButton22CooldownCountFrame" parent="BibActionButton22" hidden="true">
        <Size>
            <AbsDimension x="32" y="32"/>
        </Size>
        <Anchors>
            <Anchor point="CENTER" relativeTo="$parent" relativePoint="CENTER">
                <Offset>
                    <AbsDimension x="0" y="0"/>
                </Offset>
            </Anchor>
        </Anchors>
		<Layers>
			<Layer level="ARTWORK">
				<FontString name="BibActionButton22CooldownCount" inherits="GameFontNormalLarge" hidden="true" justifyH="CENTER">
					<Anchors>
						<Anchor point="CENTER">
							<Offset>
								<AbsDimension x="0" y="0"/>
							</Offset>
						</Anchor>
					</Anchors>
				</FontString>
			</Layer>
		</Layers>
	</Frame>
	<Frame name="BibActionButton23CooldownCountFrame" parent="BibActionButton23" hidden="true">
        <Size>
            <AbsDimension x="32" y="32"/>
        </Size>
        <Anchors>
            <Anchor point="CENTER" relativeTo="$parent" relativePoint="CENTER">
                <Offset>
                    <AbsDimension x="0" y="0"/>
                </Offset>
            </Anchor>
        </Anchors>
		<Layers>
			<Layer level="ARTWORK">
				<FontString name="BibActionButton23CooldownCount" inherits="GameFontNormalLarge" hidden="true" justifyH="CENTER">
					<Anchors>
						<Anchor point="CENTER">
							<Offset>
								<AbsDimension x="0" y="0"/>
							</Offset>
						</Anchor>
					</Anchors>
				</FontString>
			</Layer>
		</Layers>
	</Frame>
	<Frame name="BibActionButton24CooldownCountFrame" parent="BibActionButton24" hidden="true">
        <Size>
            <AbsDimension x="32" y="32"/>
        </Size>
        <Anchors>
            <Anchor point="CENTER" relativeTo="$parent" relativePoint="CENTER">
                <Offset>
                    <AbsDimension x="0" y="0"/>
                </Offset>
            </Anchor>
        </Anchors>
		<Layers>
			<Layer level="ARTWORK">
				<FontString name="BibActionButton24CooldownCount" inherits="GameFontNormalLarge" hidden="true" justifyH="CENTER">
					<Anchors>
						<Anchor point="CENTER">
							<Offset>
								<AbsDimension x="0" y="0"/>
							</Offset>
						</Anchor>
					</Anchors>
				</FontString>
			</Layer>
		</Layers>
	</Frame>
	<Frame name="BibActionButton25CooldownCountFrame" parent="BibActionButton25" hidden="true">
        <Size>
            <AbsDimension x="32" y="32"/>
        </Size>
        <Anchors>
            <Anchor point="CENTER" relativeTo="$parent" relativePoint="CENTER">
                <Offset>
                    <AbsDimension x="0" y="0"/>
                </Offset>
            </Anchor>
        </Anchors>
		<Layers>
			<Layer level="ARTWORK">
				<FontString name="BibActionButton25CooldownCount" inherits="GameFontNormalLarge" hidden="true" justifyH="CENTER">
					<Anchors>
						<Anchor point="CENTER">
							<Offset>
								<AbsDimension x="0" y="0"/>
							</Offset>
						</Anchor>
					</Anchors>
				</FontString>
			</Layer>
		</Layers>
	</Frame>
	<Frame name="BibActionButton26CooldownCountFrame" parent="BibActionButton26" hidden="true">
        <Size>
            <AbsDimension x="32" y="32"/>
        </Size>
        <Anchors>
            <Anchor point="CENTER" relativeTo="$parent" relativePoint="CENTER">
                <Offset>
                    <AbsDimension x="0" y="0"/>
                </Offset>
            </Anchor>
        </Anchors>
		<Layers>
			<Layer level="ARTWORK">
				<FontString name="BibActionButton26CooldownCount" inherits="GameFontNormalLarge" hidden="true" justifyH="CENTER">
					<Anchors>
						<Anchor point="CENTER">
							<Offset>
								<AbsDimension x="0" y="0"/>
							</Offset>
						</Anchor>
					</Anchors>
				</FontString>
			</Layer>
		</Layers>
	</Frame>
	<Frame name="BibActionButton27CooldownCountFrame" parent="BibActionButton27" hidden="true">
        <Size>
            <AbsDimension x="32" y="32"/>
        </Size>
        <Anchors>
            <Anchor point="CENTER" relativeTo="$parent" relativePoint="CENTER">
                <Offset>
                    <AbsDimension x="0" y="0"/>
                </Offset>
            </Anchor>
        </Anchors>
		<Layers>
			<Layer level="ARTWORK">
				<FontString name="BibActionButton27CooldownCount" inherits="GameFontNormalLarge" hidden="true" justifyH="CENTER">
					<Anchors>
						<Anchor point="CENTER">
							<Offset>
								<AbsDimension x="0" y="0"/>
							</Offset>
						</Anchor>
					</Anchors>
				</FontString>
			</Layer>
		</Layers>
	</Frame>
	<Frame name="BibActionButton28CooldownCountFrame" parent="BibActionButton28" hidden="true">
        <Size>
            <AbsDimension x="32" y="32"/>
        </Size>
        <Anchors>
            <Anchor point="CENTER" relativeTo="$parent" relativePoint="CENTER">
                <Offset>
                    <AbsDimension x="0" y="0"/>
                </Offset>
            </Anchor>
        </Anchors>
		<Layers>
			<Layer level="ARTWORK">
				<FontString name="BibActionButton28CooldownCount" inherits="GameFontNormalLarge" hidden="true" justifyH="CENTER">
					<Anchors>
						<Anchor point="CENTER">
							<Offset>
								<AbsDimension x="0" y="0"/>
							</Offset>
						</Anchor>
					</Anchors>
				</FontString>
			</Layer>
		</Layers>
	</Frame>
	<Frame name="BibActionButton29CooldownCountFrame" parent="BibActionButton29" hidden="true">
        <Size>
            <AbsDimension x="32" y="32"/>
        </Size>
        <Anchors>
            <Anchor point="CENTER" relativeTo="$parent" relativePoint="CENTER">
                <Offset>
                    <AbsDimension x="0" y="0"/>
                </Offset>
            </Anchor>
        </Anchors>
		<Layers>
			<Layer level="ARTWORK">
				<FontString name="BibActionButton29CooldownCount" inherits="GameFontNormalLarge" hidden="true" justifyH="CENTER">
					<Anchors>
						<Anchor point="CENTER">
							<Offset>
								<AbsDimension x="0" y="0"/>
							</Offset>
						</Anchor>
					</Anchors>
				</FontString>
			</Layer>
		</Layers>
	</Frame>

	<Frame name="BibActionButton30CooldownCountFrame" parent="BibActionButton30" hidden="true">
        <Size>
            <AbsDimension x="32" y="32"/>
        </Size>
        <Anchors>
            <Anchor point="CENTER" relativeTo="$parent" relativePoint="CENTER">
                <Offset>
                    <AbsDimension x="0" y="0"/>
                </Offset>
            </Anchor>
        </Anchors>
		<Layers>
			<Layer level="ARTWORK">
				<FontString name="BibActionButton30CooldownCount" inherits="GameFontNormalLarge" hidden="true" justifyH="CENTER">
					<Anchors>
						<Anchor point="CENTER">
							<Offset>
								<AbsDimension x="0" y="0"/>
							</Offset>
						</Anchor>
					</Anchors>
				</FontString>
			</Layer>
		</Layers>
	</Frame>
	<Frame name="BibActionButton31CooldownCountFrame" parent="BibActionButton31" hidden="true">
        <Size>
            <AbsDimension x="32" y="32"/>
        </Size>
        <Anchors>
            <Anchor point="CENTER" relativeTo="$parent" relativePoint="CENTER">
                <Offset>
                    <AbsDimension x="0" y="0"/>
                </Offset>
            </Anchor>
        </Anchors>
		<Layers>
			<Layer level="ARTWORK">
				<FontString name="BibActionButton31CooldownCount" inherits="GameFontNormalLarge" hidden="true" justifyH="CENTER">
					<Anchors>
						<Anchor point="CENTER">
							<Offset>
								<AbsDimension x="0" y="0"/>
							</Offset>
						</Anchor>
					</Anchors>
				</FontString>
			</Layer>
		</Layers>
	</Frame>
	<Frame name="BibActionButton32CooldownCountFrame" parent="BibActionButton32" hidden="true">
        <Size>
            <AbsDimension x="32" y="32"/>
        </Size>
        <Anchors>
            <Anchor point="CENTER" relativeTo="$parent" relativePoint="CENTER">
                <Offset>
                    <AbsDimension x="0" y="0"/>
                </Offset>
            </Anchor>
        </Anchors>
		<Layers>
			<Layer level="ARTWORK">
				<FontString name="BibActionButton32CooldownCount" inherits="GameFontNormalLarge" hidden="true" justifyH="CENTER">
					<Anchors>
						<Anchor point="CENTER">
							<Offset>
								<AbsDimension x="0" y="0"/>
							</Offset>
						</Anchor>
					</Anchors>
				</FontString>
			</Layer>
		</Layers>
	</Frame>
	<Frame name="BibActionButton33CooldownCountFrame" parent="BibActionButton33" hidden="true">
        <Size>
            <AbsDimension x="32" y="32"/>
        </Size>
        <Anchors>
            <Anchor point="CENTER" relativeTo="$parent" relativePoint="CENTER">
                <Offset>
                    <AbsDimension x="0" y="0"/>
                </Offset>
            </Anchor>
        </Anchors>
		<Layers>
			<Layer level="ARTWORK">
				<FontString name="BibActionButton33CooldownCount" inherits="GameFontNormalLarge" hidden="true" justifyH="CENTER">
					<Anchors>
						<Anchor point="CENTER">
							<Offset>
								<AbsDimension x="0" y="0"/>
							</Offset>
						</Anchor>
					</Anchors>
				</FontString>
			</Layer>
		</Layers>
	</Frame>
	<Frame name="BibActionButton34CooldownCountFrame" parent="BibActionButton34" hidden="true">
        <Size>
            <AbsDimension x="32" y="32"/>
        </Size>
        <Anchors>
            <Anchor point="CENTER" relativeTo="$parent" relativePoint="CENTER">
                <Offset>
                    <AbsDimension x="0" y="0"/>
                </Offset>
            </Anchor>
        </Anchors>
		<Layers>
			<Layer level="ARTWORK">
				<FontString name="BibActionButton34CooldownCount" inherits="GameFontNormalLarge" hidden="true" justifyH="CENTER">
					<Anchors>
						<Anchor point="CENTER">
							<Offset>
								<AbsDimension x="0" y="0"/>
							</Offset>
						</Anchor>
					</Anchors>
				</FontString>
			</Layer>
		</Layers>
	</Frame>
	<Frame name="BibActionButton35CooldownCountFrame" parent="BibActionButton35" hidden="true">
        <Size>
            <AbsDimension x="32" y="32"/>
        </Size>
        <Anchors>
            <Anchor point="CENTER" relativeTo="$parent" relativePoint="CENTER">
                <Offset>
                    <AbsDimension x="0" y="0"/>
                </Offset>
            </Anchor>
        </Anchors>
		<Layers>
			<Layer level="ARTWORK">
				<FontString name="BibActionButton35CooldownCount" inherits="GameFontNormalLarge" hidden="true" justifyH="CENTER">
					<Anchors>
						<Anchor point="CENTER">
							<Offset>
								<AbsDimension x="0" y="0"/>
							</Offset>
						</Anchor>
					</Anchors>
				</FontString>
			</Layer>
		</Layers>
	</Frame>
	<Frame name="BibActionButton36CooldownCountFrame" parent="BibActionButton36" hidden="true">
        <Size>
            <AbsDimension x="32" y="32"/>
        </Size>
        <Anchors>
            <Anchor point="CENTER" relativeTo="$parent" relativePoint="CENTER">
                <Offset>
                    <AbsDimension x="0" y="0"/>
                </Offset>
            </Anchor>
        </Anchors>
		<Layers>
			<Layer level="ARTWORK">
				<FontString name="BibActionButton36CooldownCount" inherits="GameFontNormalLarge" hidden="true" justifyH="CENTER">
					<Anchors>
						<Anchor point="CENTER">
							<Offset>
								<AbsDimension x="0" y="0"/>
							</Offset>
						</Anchor>
					</Anchors>
				</FontString>
			</Layer>
		</Layers>
	</Frame>
	<Frame name="BibActionButton37CooldownCountFrame" parent="BibActionButton37" hidden="true">
        <Size>
            <AbsDimension x="32" y="32"/>
        </Size>
        <Anchors>
            <Anchor point="CENTER" relativeTo="$parent" relativePoint="CENTER">
                <Offset>
                    <AbsDimension x="0" y="0"/>
                </Offset>
            </Anchor>
        </Anchors>
		<Layers>
			<Layer level="ARTWORK">
				<FontString name="BibActionButton37CooldownCount" inherits="GameFontNormalLarge" hidden="true" justifyH="CENTER">
					<Anchors>
						<Anchor point="CENTER">
							<Offset>
								<AbsDimension x="0" y="0"/>
							</Offset>
						</Anchor>
					</Anchors>
				</FontString>
			</Layer>
		</Layers>
	</Frame>
	<Frame name="BibActionButton38CooldownCountFrame" parent="BibActionButton38" hidden="true">
        <Size>
            <AbsDimension x="32" y="32"/>
        </Size>
        <Anchors>
            <Anchor point="CENTER" relativeTo="$parent" relativePoint="CENTER">
                <Offset>
                    <AbsDimension x="0" y="0"/>
                </Offset>
            </Anchor>
        </Anchors>
		<Layers>
			<Layer level="ARTWORK">
				<FontString name="BibActionButton38CooldownCount" inherits="GameFontNormalLarge" hidden="true" justifyH="CENTER">
					<Anchors>
						<Anchor point="CENTER">
							<Offset>
								<AbsDimension x="0" y="0"/>
							</Offset>
						</Anchor>
					</Anchors>
				</FontString>
			</Layer>
		</Layers>
	</Frame>
	<Frame name="BibActionButton39CooldownCountFrame" parent="BibActionButton39" hidden="true">
        <Size>
            <AbsDimension x="32" y="32"/>
        </Size>
        <Anchors>
            <Anchor point="CENTER" relativeTo="$parent" relativePoint="CENTER">
                <Offset>
                    <AbsDimension x="0" y="0"/>
                </Offset>
            </Anchor>
        </Anchors>
		<Layers>
			<Layer level="ARTWORK">
				<FontString name="BibActionButton39CooldownCount" inherits="GameFontNormalLarge" hidden="true" justifyH="CENTER">
					<Anchors>
						<Anchor point="CENTER">
							<Offset>
								<AbsDimension x="0" y="0"/>
							</Offset>
						</Anchor>
					</Anchors>
				</FontString>
			</Layer>
		</Layers>
	</Frame>

	<Frame name="BibActionButton40CooldownCountFrame" parent="BibActionButton40" hidden="true">
        <Size>
            <AbsDimension x="32" y="32"/>
        </Size>
        <Anchors>
            <Anchor point="CENTER" relativeTo="$parent" relativePoint="CENTER">
                <Offset>
                    <AbsDimension x="0" y="0"/>
                </Offset>
            </Anchor>
        </Anchors>
		<Layers>
			<Layer level="ARTWORK">
				<FontString name="BibActionButton40CooldownCount" inherits="GameFontNormalLarge" hidden="true" justifyH="CENTER">
					<Anchors>
						<Anchor point="CENTER">
							<Offset>
								<AbsDimension x="0" y="0"/>
							</Offset>
						</Anchor>
					</Anchors>
				</FontString>
			</Layer>
		</Layers>
	</Frame>
	<Frame name="BibActionButton41CooldownCountFrame" parent="BibActionButton41" hidden="true">
        <Size>
            <AbsDimension x="32" y="32"/>
        </Size>
        <Anchors>
            <Anchor point="CENTER" relativeTo="$parent" relativePoint="CENTER">
                <Offset>
                    <AbsDimension x="0" y="0"/>
                </Offset>
            </Anchor>
        </Anchors>
		<Layers>
			<Layer level="ARTWORK">
				<FontString name="BibActionButton41CooldownCount" inherits="GameFontNormalLarge" hidden="true" justifyH="CENTER">
					<Anchors>
						<Anchor point="CENTER">
							<Offset>
								<AbsDimension x="0" y="0"/>
							</Offset>
						</Anchor>
					</Anchors>
				</FontString>
			</Layer>
		</Layers>
	</Frame>
	<Frame name="BibActionButton42CooldownCountFrame" parent="BibActionButton42" hidden="true">
        <Size>
            <AbsDimension x="32" y="32"/>
        </Size>
        <Anchors>
            <Anchor point="CENTER" relativeTo="$parent" relativePoint="CENTER">
                <Offset>
                    <AbsDimension x="0" y="0"/>
                </Offset>
            </Anchor>
        </Anchors>
		<Layers>
			<Layer level="ARTWORK">
				<FontString name="BibActionButton42CooldownCount" inherits="GameFontNormalLarge" hidden="true" justifyH="CENTER">
					<Anchors>
						<Anchor point="CENTER">
							<Offset>
								<AbsDimension x="0" y="0"/>
							</Offset>
						</Anchor>
					</Anchors>
				</FontString>
			</Layer>
		</Layers>
	</Frame>
	<Frame name="BibActionButton43CooldownCountFrame" parent="BibActionButton43" hidden="true">
        <Size>
            <AbsDimension x="32" y="32"/>
        </Size>
        <Anchors>
            <Anchor point="CENTER" relativeTo="$parent" relativePoint="CENTER">
                <Offset>
                    <AbsDimension x="0" y="0"/>
                </Offset>
            </Anchor>
        </Anchors>
		<Layers>
			<Layer level="ARTWORK">
				<FontString name="BibActionButton43CooldownCount" inherits="GameFontNormalLarge" hidden="true" justifyH="CENTER">
					<Anchors>
						<Anchor point="CENTER">
							<Offset>
								<AbsDimension x="0" y="0"/>
							</Offset>
						</Anchor>
					</Anchors>
				</FontString>
			</Layer>
		</Layers>
	</Frame>
	<Frame name="BibActionButton44CooldownCountFrame" parent="BibActionButton44" hidden="true">
        <Size>
            <AbsDimension x="32" y="32"/>
        </Size>
        <Anchors>
            <Anchor point="CENTER" relativeTo="$parent" relativePoint="CENTER">
                <Offset>
                    <AbsDimension x="0" y="0"/>
                </Offset>
            </Anchor>
        </Anchors>
		<Layers>
			<Layer level="ARTWORK">
				<FontString name="BibActionButton44CooldownCount" inherits="GameFontNormalLarge" hidden="true" justifyH="CENTER">
					<Anchors>
						<Anchor point="CENTER">
							<Offset>
								<AbsDimension x="0" y="0"/>
							</Offset>
						</Anchor>
					</Anchors>
				</FontString>
			</Layer>
		</Layers>
	</Frame>
	<Frame name="BibActionButton45CooldownCountFrame" parent="BibActionButton45" hidden="true">
        <Size>
            <AbsDimension x="32" y="32"/>
        </Size>
        <Anchors>
            <Anchor point="CENTER" relativeTo="$parent" relativePoint="CENTER">
                <Offset>
                    <AbsDimension x="0" y="0"/>
                </Offset>
            </Anchor>
        </Anchors>
		<Layers>
			<Layer level="ARTWORK">
				<FontString name="BibActionButton45CooldownCount" inherits="GameFontNormalLarge" hidden="true" justifyH="CENTER">
					<Anchors>
						<Anchor point="CENTER">
							<Offset>
								<AbsDimension x="0" y="0"/>
							</Offset>
						</Anchor>
					</Anchors>
				</FontString>
			</Layer>
		</Layers>
	</Frame>
	<Frame name="BibActionButton46CooldownCountFrame" parent="BibActionButton46" hidden="true">
        <Size>
            <AbsDimension x="32" y="32"/>
        </Size>
        <Anchors>
            <Anchor point="CENTER" relativeTo="$parent" relativePoint="CENTER">
                <Offset>
                    <AbsDimension x="0" y="0"/>
                </Offset>
            </Anchor>
        </Anchors>
		<Layers>
			<Layer level="ARTWORK">
				<FontString name="BibActionButton46CooldownCount" inherits="GameFontNormalLarge" hidden="true" justifyH="CENTER">
					<Anchors>
						<Anchor point="CENTER">
							<Offset>
								<AbsDimension x="0" y="0"/>
							</Offset>
						</Anchor>
					</Anchors>
				</FontString>
			</Layer>
		</Layers>
	</Frame>
	<Frame name="BibActionButton47CooldownCountFrame" parent="BibActionButton47" hidden="true">
        <Size>
            <AbsDimension x="32" y="32"/>
        </Size>
        <Anchors>
            <Anchor point="CENTER" relativeTo="$parent" relativePoint="CENTER">
                <Offset>
                    <AbsDimension x="0" y="0"/>
                </Offset>
            </Anchor>
        </Anchors>
		<Layers>
			<Layer level="ARTWORK">
				<FontString name="BibActionButton47CooldownCount" inherits="GameFontNormalLarge" hidden="true" justifyH="CENTER">
					<Anchors>
						<Anchor point="CENTER">
							<Offset>
								<AbsDimension x="0" y="0"/>
							</Offset>
						</Anchor>
					</Anchors>
				</FontString>
			</Layer>
		</Layers>
	</Frame>
	<Frame name="BibActionButton48CooldownCountFrame" parent="BibActionButton48" hidden="true">
        <Size>
            <AbsDimension x="32" y="32"/>
        </Size>
        <Anchors>
            <Anchor point="CENTER" relativeTo="$parent" relativePoint="CENTER">
                <Offset>
                    <AbsDimension x="0" y="0"/>
                </Offset>
            </Anchor>
        </Anchors>
		<Layers>
			<Layer level="ARTWORK">
				<FontString name="BibActionButton48CooldownCount" inherits="GameFontNormalLarge" hidden="true" justifyH="CENTER">
					<Anchors>
						<Anchor point="CENTER">
							<Offset>
								<AbsDimension x="0" y="0"/>
							</Offset>
						</Anchor>
					</Anchors>
				</FontString>
			</Layer>
		</Layers>
	</Frame>
	<Frame name="BibActionButton49CooldownCountFrame" parent="BibActionButton49" hidden="true">
        <Size>
            <AbsDimension x="32" y="32"/>
        </Size>
        <Anchors>
            <Anchor point="CENTER" relativeTo="$parent" relativePoint="CENTER">
                <Offset>
                    <AbsDimension x="0" y="0"/>
                </Offset>
            </Anchor>
        </Anchors>
		<Layers>
			<Layer level="ARTWORK">
				<FontString name="BibActionButton49CooldownCount" inherits="GameFontNormalLarge" hidden="true" justifyH="CENTER">
					<Anchors>
						<Anchor point="CENTER">
							<Offset>
								<AbsDimension x="0" y="0"/>
							</Offset>
						</Anchor>
					</Anchors>
				</FontString>
			</Layer>
		</Layers>
	</Frame>

	<Frame name="BibActionButton50CooldownCountFrame" parent="BibActionButton50" hidden="true">
        <Size>
            <AbsDimension x="32" y="32"/>
        </Size>
        <Anchors>
            <Anchor point="CENTER" relativeTo="$parent" relativePoint="CENTER">
                <Offset>
                    <AbsDimension x="0" y="0"/>
                </Offset>
            </Anchor>
        </Anchors>
		<Layers>
			<Layer level="ARTWORK">
				<FontString name="BibActionButton50CooldownCount" inherits="GameFontNormalLarge" hidden="true" justifyH="CENTER">
					<Anchors>
						<Anchor point="CENTER">
							<Offset>
								<AbsDimension x="0" y="0"/>
							</Offset>
						</Anchor>
					</Anchors>
				</FontString>
			</Layer>
		</Layers>
	</Frame>
	<Frame name="BibActionButton51CooldownCountFrame" parent="BibActionButton51" hidden="true">
        <Size>
            <AbsDimension x="32" y="32"/>
        </Size>
        <Anchors>
            <Anchor point="CENTER" relativeTo="$parent" relativePoint="CENTER">
                <Offset>
                    <AbsDimension x="0" y="0"/>
                </Offset>
            </Anchor>
        </Anchors>
		<Layers>
			<Layer level="ARTWORK">
				<FontString name="BibActionButton51CooldownCount" inherits="GameFontNormalLarge" hidden="true" justifyH="CENTER">
					<Anchors>
						<Anchor point="CENTER">
							<Offset>
								<AbsDimension x="0" y="0"/>
							</Offset>
						</Anchor>
					</Anchors>
				</FontString>
			</Layer>
		</Layers>
	</Frame>
	<Frame name="BibActionButton52CooldownCountFrame" parent="BibActionButton52" hidden="true">
        <Size>
            <AbsDimension x="32" y="32"/>
        </Size>
        <Anchors>
            <Anchor point="CENTER" relativeTo="$parent" relativePoint="CENTER">
                <Offset>
                    <AbsDimension x="0" y="0"/>
                </Offset>
            </Anchor>
        </Anchors>
		<Layers>
			<Layer level="ARTWORK">
				<FontString name="BibActionButton52CooldownCount" inherits="GameFontNormalLarge" hidden="true" justifyH="CENTER">
					<Anchors>
						<Anchor point="CENTER">
							<Offset>
								<AbsDimension x="0" y="0"/>
							</Offset>
						</Anchor>
					</Anchors>
				</FontString>
			</Layer>
		</Layers>
	</Frame>
	<Frame name="BibActionButton53CooldownCountFrame" parent="BibActionButton53" hidden="true">
        <Size>
            <AbsDimension x="32" y="32"/>
        </Size>
        <Anchors>
            <Anchor point="CENTER" relativeTo="$parent" relativePoint="CENTER">
                <Offset>
                    <AbsDimension x="0" y="0"/>
                </Offset>
            </Anchor>
        </Anchors>
		<Layers>
			<Layer level="ARTWORK">
				<FontString name="BibActionButton53CooldownCount" inherits="GameFontNormalLarge" hidden="true" justifyH="CENTER">
					<Anchors>
						<Anchor point="CENTER">
							<Offset>
								<AbsDimension x="0" y="0"/>
							</Offset>
						</Anchor>
					</Anchors>
				</FontString>
			</Layer>
		</Layers>
	</Frame>
	<Frame name="BibActionButton54CooldownCountFrame" parent="BibActionButton54" hidden="true">
        <Size>
            <AbsDimension x="32" y="32"/>
        </Size>
        <Anchors>
            <Anchor point="CENTER" relativeTo="$parent" relativePoint="CENTER">
                <Offset>
                    <AbsDimension x="0" y="0"/>
                </Offset>
            </Anchor>
        </Anchors>
		<Layers>
			<Layer level="ARTWORK">
				<FontString name="BibActionButton54CooldownCount" inherits="GameFontNormalLarge" hidden="true" justifyH="CENTER">
					<Anchors>
						<Anchor point="CENTER">
							<Offset>
								<AbsDimension x="0" y="0"/>
							</Offset>
						</Anchor>
					</Anchors>
				</FontString>
			</Layer>
		</Layers>
	</Frame>
	<Frame name="BibActionButton55CooldownCountFrame" parent="BibActionButton55" hidden="true">
        <Size>
            <AbsDimension x="32" y="32"/>
        </Size>
        <Anchors>
            <Anchor point="CENTER" relativeTo="$parent" relativePoint="CENTER">
                <Offset>
                    <AbsDimension x="0" y="0"/>
                </Offset>
            </Anchor>
        </Anchors>
		<Layers>
			<Layer level="ARTWORK">
				<FontString name="BibActionButton55CooldownCount" inherits="GameFontNormalLarge" hidden="true" justifyH="CENTER">
					<Anchors>
						<Anchor point="CENTER">
							<Offset>
								<AbsDimension x="0" y="0"/>
							</Offset>
						</Anchor>
					</Anchors>
				</FontString>
			</Layer>
		</Layers>
	</Frame>
	<Frame name="BibActionButton56CooldownCountFrame" parent="BibActionButton56" hidden="true">
        <Size>
            <AbsDimension x="32" y="32"/>
        </Size>
        <Anchors>
            <Anchor point="CENTER" relativeTo="$parent" relativePoint="CENTER">
                <Offset>
                    <AbsDimension x="0" y="0"/>
                </Offset>
            </Anchor>
        </Anchors>
		<Layers>
			<Layer level="ARTWORK">
				<FontString name="BibActionButton56CooldownCount" inherits="GameFontNormalLarge" hidden="true" justifyH="CENTER">
					<Anchors>
						<Anchor point="CENTER">
							<Offset>
								<AbsDimension x="0" y="0"/>
							</Offset>
						</Anchor>
					</Anchors>
				</FontString>
			</Layer>
		</Layers>
	</Frame>
	<Frame name="BibActionButton57CooldownCountFrame" parent="BibActionButton57" hidden="true">
        <Size>
            <AbsDimension x="32" y="32"/>
        </Size>
        <Anchors>
            <Anchor point="CENTER" relativeTo="$parent" relativePoint="CENTER">
                <Offset>
                    <AbsDimension x="0" y="0"/>
                </Offset>
            </Anchor>
        </Anchors>
		<Layers>
			<Layer level="ARTWORK">
				<FontString name="BibActionButton57CooldownCount" inherits="GameFontNormalLarge" hidden="true" justifyH="CENTER">
					<Anchors>
						<Anchor point="CENTER">
							<Offset>
								<AbsDimension x="0" y="0"/>
							</Offset>
						</Anchor>
					</Anchors>
				</FontString>
			</Layer>
		</Layers>
	</Frame>
	<Frame name="BibActionButton58CooldownCountFrame" parent="BibActionButton58" hidden="true">
        <Size>
            <AbsDimension x="32" y="32"/>
        </Size>
        <Anchors>
            <Anchor point="CENTER" relativeTo="$parent" relativePoint="CENTER">
                <Offset>
                    <AbsDimension x="0" y="0"/>
                </Offset>
            </Anchor>
        </Anchors>
		<Layers>
			<Layer level="ARTWORK">
				<FontString name="BibActionButton58CooldownCount" inherits="GameFontNormalLarge" hidden="true" justifyH="CENTER">
					<Anchors>
						<Anchor point="CENTER">
							<Offset>
								<AbsDimension x="0" y="0"/>
							</Offset>
						</Anchor>
					</Anchors>
				</FontString>
			</Layer>
		</Layers>
	</Frame>
	<Frame name="BibActionButton59CooldownCountFrame" parent="BibActionButton59" hidden="true">
        <Size>
            <AbsDimension x="32" y="32"/>
        </Size>
        <Anchors>
            <Anchor point="CENTER" relativeTo="$parent" relativePoint="CENTER">
                <Offset>
                    <AbsDimension x="0" y="0"/>
                </Offset>
            </Anchor>
        </Anchors>
		<Layers>
			<Layer level="ARTWORK">
				<FontString name="BibActionButton59CooldownCount" inherits="GameFontNormalLarge" hidden="true" justifyH="CENTER">
					<Anchors>
						<Anchor point="CENTER">
							<Offset>
								<AbsDimension x="0" y="0"/>
							</Offset>
						</Anchor>
					</Anchors>
				</FontString>
			</Layer>
		</Layers>
	</Frame>

	<Frame name="BibActionButton60CooldownCountFrame" parent="BibActionButton60" hidden="true">
        <Size>
            <AbsDimension x="32" y="32"/>
        </Size>
        <Anchors>
            <Anchor point="CENTER" relativeTo="$parent" relativePoint="CENTER">
                <Offset>
                    <AbsDimension x="0" y="0"/>
                </Offset>
            </Anchor>
        </Anchors>
		<Layers>
			<Layer level="ARTWORK">
				<FontString name="BibActionButton60CooldownCount" inherits="GameFontNormalLarge" hidden="true" justifyH="CENTER">
					<Anchors>
						<Anchor point="CENTER">
							<Offset>
								<AbsDimension x="0" y="0"/>
							</Offset>
						</Anchor>
					</Anchors>
				</FontString>
			</Layer>
		</Layers>
	</Frame>
	<Frame name="BibActionButton61CooldownCountFrame" parent="BibActionButton61" hidden="true">
        <Size>
            <AbsDimension x="32" y="32"/>
        </Size>
        <Anchors>
            <Anchor point="CENTER" relativeTo="$parent" relativePoint="CENTER">
                <Offset>
                    <AbsDimension x="0" y="0"/>
                </Offset>
            </Anchor>
        </Anchors>
		<Layers>
			<Layer level="ARTWORK">
				<FontString name="BibActionButton61CooldownCount" inherits="GameFontNormalLarge" hidden="true" justifyH="CENTER">
					<Anchors>
						<Anchor point="CENTER">
							<Offset>
								<AbsDimension x="0" y="0"/>
							</Offset>
						</Anchor>
					</Anchors>
				</FontString>
			</Layer>
		</Layers>
	</Frame>
	<Frame name="BibActionButton62CooldownCountFrame" parent="BibActionButton62" hidden="true">
        <Size>
            <AbsDimension x="32" y="32"/>
        </Size>
        <Anchors>
            <Anchor point="CENTER" relativeTo="$parent" relativePoint="CENTER">
                <Offset>
                    <AbsDimension x="0" y="0"/>
                </Offset>
            </Anchor>
        </Anchors>
		<Layers>
			<Layer level="ARTWORK">
				<FontString name="BibActionButton62CooldownCount" inherits="GameFontNormalLarge" hidden="true" justifyH="CENTER">
					<Anchors>
						<Anchor point="CENTER">
							<Offset>
								<AbsDimension x="0" y="0"/>
							</Offset>
						</Anchor>
					</Anchors>
				</FontString>
			</Layer>
		</Layers>
	</Frame>
	<Frame name="BibActionButton63CooldownCountFrame" parent="BibActionButton63" hidden="true">
        <Size>
            <AbsDimension x="32" y="32"/>
        </Size>
        <Anchors>
            <Anchor point="CENTER" relativeTo="$parent" relativePoint="CENTER">
                <Offset>
                    <AbsDimension x="0" y="0"/>
                </Offset>
            </Anchor>
        </Anchors>
		<Layers>
			<Layer level="ARTWORK">
				<FontString name="BibActionButton63CooldownCount" inherits="GameFontNormalLarge" hidden="true" justifyH="CENTER">
					<Anchors>
						<Anchor point="CENTER">
							<Offset>
								<AbsDimension x="0" y="0"/>
							</Offset>
						</Anchor>
					</Anchors>
				</FontString>
			</Layer>
		</Layers>
	</Frame>
	<Frame name="BibActionButton64CooldownCountFrame" parent="BibActionButton64" hidden="true">
        <Size>
            <AbsDimension x="32" y="32"/>
        </Size>
        <Anchors>
            <Anchor point="CENTER" relativeTo="$parent" relativePoint="CENTER">
                <Offset>
                    <AbsDimension x="0" y="0"/>
                </Offset>
            </Anchor>
        </Anchors>
		<Layers>
			<Layer level="ARTWORK">
				<FontString name="BibActionButton64CooldownCount" inherits="GameFontNormalLarge" hidden="true" justifyH="CENTER">
					<Anchors>
						<Anchor point="CENTER">
							<Offset>
								<AbsDimension x="0" y="0"/>
							</Offset>
						</Anchor>
					</Anchors>
				</FontString>
			</Layer>
		</Layers>
	</Frame>
	<Frame name="BibActionButton65CooldownCountFrame" parent="BibActionButton65" hidden="true">
        <Size>
            <AbsDimension x="32" y="32"/>
        </Size>
        <Anchors>
            <Anchor point="CENTER" relativeTo="$parent" relativePoint="CENTER">
                <Offset>
                    <AbsDimension x="0" y="0"/>
                </Offset>
            </Anchor>
        </Anchors>
		<Layers>
			<Layer level="ARTWORK">
				<FontString name="BibActionButton65CooldownCount" inherits="GameFontNormalLarge" hidden="true" justifyH="CENTER">
					<Anchors>
						<Anchor point="CENTER">
							<Offset>
								<AbsDimension x="0" y="0"/>
							</Offset>
						</Anchor>
					</Anchors>
				</FontString>
			</Layer>
		</Layers>
	</Frame>
	<Frame name="BibActionButton66CooldownCountFrame" parent="BibActionButton66" hidden="true">
        <Size>
            <AbsDimension x="32" y="32"/>
        </Size>
        <Anchors>
            <Anchor point="CENTER" relativeTo="$parent" relativePoint="CENTER">
                <Offset>
                    <AbsDimension x="0" y="0"/>
                </Offset>
            </Anchor>
        </Anchors>
		<Layers>
			<Layer level="ARTWORK">
				<FontString name="BibActionButton66CooldownCount" inherits="GameFontNormalLarge" hidden="true" justifyH="CENTER">
					<Anchors>
						<Anchor point="CENTER">
							<Offset>
								<AbsDimension x="0" y="0"/>
							</Offset>
						</Anchor>
					</Anchors>
				</FontString>
			</Layer>
		</Layers>
	</Frame>
	<Frame name="BibActionButton67CooldownCountFrame" parent="BibActionButton67" hidden="true">
        <Size>
            <AbsDimension x="32" y="32"/>
        </Size>
        <Anchors>
            <Anchor point="CENTER" relativeTo="$parent" relativePoint="CENTER">
                <Offset>
                    <AbsDimension x="0" y="0"/>
                </Offset>
            </Anchor>
        </Anchors>
		<Layers>
			<Layer level="ARTWORK">
				<FontString name="BibActionButton67CooldownCount" inherits="GameFontNormalLarge" hidden="true" justifyH="CENTER">
					<Anchors>
						<Anchor point="CENTER">
							<Offset>
								<AbsDimension x="0" y="0"/>
							</Offset>
						</Anchor>
					</Anchors>
				</FontString>
			</Layer>
		</Layers>
	</Frame>
	<Frame name="BibActionButton68CooldownCountFrame" parent="BibActionButton68" hidden="true">
        <Size>
            <AbsDimension x="32" y="32"/>
        </Size>
        <Anchors>
            <Anchor point="CENTER" relativeTo="$parent" relativePoint="CENTER">
                <Offset>
                    <AbsDimension x="0" y="0"/>
                </Offset>
            </Anchor>
        </Anchors>
		<Layers>
			<Layer level="ARTWORK">
				<FontString name="BibActionButton68CooldownCount" inherits="GameFontNormalLarge" hidden="true" justifyH="CENTER">
					<Anchors>
						<Anchor point="CENTER">
							<Offset>
								<AbsDimension x="0" y="0"/>
							</Offset>
						</Anchor>
					</Anchors>
				</FontString>
			</Layer>
		</Layers>
	</Frame>
	<Frame name="BibActionButton69CooldownCountFrame" parent="BibActionButton69" hidden="true">
        <Size>
            <AbsDimension x="32" y="32"/>
        </Size>
        <Anchors>
            <Anchor point="CENTER" relativeTo="$parent" relativePoint="CENTER">
                <Offset>
                    <AbsDimension x="0" y="0"/>
                </Offset>
            </Anchor>
        </Anchors>
		<Layers>
			<Layer level="ARTWORK">
				<FontString name="BibActionButton69CooldownCount" inherits="GameFontNormalLarge" hidden="true" justifyH="CENTER">
					<Anchors>
						<Anchor point="CENTER">
							<Offset>
								<AbsDimension x="0" y="0"/>
							</Offset>
						</Anchor>
					</Anchors>
				</FontString>
			</Layer>
		</Layers>
	</Frame>
	<Frame name="BibActionButton70CooldownCountFrame" parent="BibActionButton70" hidden="true">
        <Size>
            <AbsDimension x="32" y="32"/>
        </Size>
        <Anchors>
            <Anchor point="CENTER" relativeTo="$parent" relativePoint="CENTER">
                <Offset>
                    <AbsDimension x="0" y="0"/>
                </Offset>
            </Anchor>
        </Anchors>
		<Layers>
			<Layer level="ARTWORK">
				<FontString name="BibActionButton70CooldownCount" inherits="GameFontNormalLarge" hidden="true" justifyH="CENTER">
					<Anchors>
						<Anchor point="CENTER">
							<Offset>
								<AbsDimension x="0" y="0"/>
							</Offset>
						</Anchor>
					</Anchors>
				</FontString>
			</Layer>
		</Layers>
	</Frame>
	<Frame name="BibActionButton71CooldownCountFrame" parent="BibActionButton71" hidden="true">
        <Size>
            <AbsDimension x="32" y="32"/>
        </Size>
        <Anchors>
            <Anchor point="CENTER" relativeTo="$parent" relativePoint="CENTER">
                <Offset>
                    <AbsDimension x="0" y="0"/>
                </Offset>
            </Anchor>
        </Anchors>
		<Layers>
			<Layer level="ARTWORK">
				<FontString name="BibActionButton71CooldownCount" inherits="GameFontNormalLarge" hidden="true" justifyH="CENTER">
					<Anchors>
						<Anchor point="CENTER">
							<Offset>
								<AbsDimension x="0" y="0"/>
							</Offset>
						</Anchor>
					</Anchors>
				</FontString>
			</Layer>
		</Layers>
	</Frame>
	<Frame name="BibActionButton72CooldownCountFrame" parent="BibActionButton72" hidden="true">
        <Size>
            <AbsDimension x="32" y="32"/>
        </Size>
        <Anchors>
            <Anchor point="CENTER" relativeTo="$parent" relativePoint="CENTER">
                <Offset>
                    <AbsDimension x="0" y="0"/>
                </Offset>
            </Anchor>
        </Anchors>
		<Layers>
			<Layer level="ARTWORK">
				<FontString name="BibActionButton72CooldownCount" inherits="GameFontNormalLarge" hidden="true" justifyH="CENTER">
					<Anchors>
						<Anchor point="CENTER">
							<Offset>
								<AbsDimension x="0" y="0"/>
							</Offset>
						</Anchor>
					</Anchors>
				</FontString>
			</Layer>
		</Layers>
	</Frame>
	<Frame name="BibActionButton73CooldownCountFrame" parent="BibActionButton73" hidden="true">
        <Size>
            <AbsDimension x="32" y="32"/>
        </Size>
        <Anchors>
            <Anchor point="CENTER" relativeTo="$parent" relativePoint="CENTER">
                <Offset>
                    <AbsDimension x="0" y="0"/>
                </Offset>
            </Anchor>
        </Anchors>
		<Layers>
			<Layer level="ARTWORK">
				<FontString name="BibActionButton73CooldownCount" inherits="GameFontNormalLarge" hidden="true" justifyH="CENTER">
					<Anchors>
						<Anchor point="CENTER">
							<Offset>
								<AbsDimension x="0" y="0"/>
							</Offset>
						</Anchor>
					</Anchors>
				</FontString>
			</Layer>
		</Layers>
	</Frame>
	<Frame name="BibActionButton74CooldownCountFrame" parent="BibActionButton74" hidden="true">
        <Size>
            <AbsDimension x="32" y="32"/>
        </Size>
        <Anchors>
            <Anchor point="CENTER" relativeTo="$parent" relativePoint="CENTER">
                <Offset>
                    <AbsDimension x="0" y="0"/>
                </Offset>
            </Anchor>
        </Anchors>
		<Layers>
			<Layer level="ARTWORK">
				<FontString name="BibActionButton74CooldownCount" inherits="GameFontNormalLarge" hidden="true" justifyH="CENTER">
					<Anchors>
						<Anchor point="CENTER">
							<Offset>
								<AbsDimension x="0" y="0"/>
							</Offset>
						</Anchor>
					</Anchors>
				</FontString>
			</Layer>
		</Layers>
	</Frame>
	<Frame name="BibActionButton75CooldownCountFrame" parent="BibActionButton75" hidden="true">
        <Size>
            <AbsDimension x="32" y="32"/>
        </Size>
        <Anchors>
            <Anchor point="CENTER" relativeTo="$parent" relativePoint="CENTER">
                <Offset>
                    <AbsDimension x="0" y="0"/>
                </Offset>
            </Anchor>
        </Anchors>
		<Layers>
			<Layer level="ARTWORK">
				<FontString name="BibActionButton75CooldownCount" inherits="GameFontNormalLarge" hidden="true" justifyH="CENTER">
					<Anchors>
						<Anchor point="CENTER">
							<Offset>
								<AbsDimension x="0" y="0"/>
							</Offset>
						</Anchor>
					</Anchors>
				</FontString>
			</Layer>
		</Layers>
	</Frame>
	<Frame name="BibActionButton76CooldownCountFrame" parent="BibActionButton76" hidden="true">
        <Size>
            <AbsDimension x="32" y="32"/>
        </Size>
        <Anchors>
            <Anchor point="CENTER" relativeTo="$parent" relativePoint="CENTER">
                <Offset>
                    <AbsDimension x="0" y="0"/>
                </Offset>
            </Anchor>
        </Anchors>
		<Layers>
			<Layer level="ARTWORK">
				<FontString name="BibActionButton76CooldownCount" inherits="GameFontNormalLarge" hidden="true" justifyH="CENTER">
					<Anchors>
						<Anchor point="CENTER">
							<Offset>
								<AbsDimension x="0" y="0"/>
							</Offset>
						</Anchor>
					</Anchors>
				</FontString>
			</Layer>
		</Layers>
	</Frame>
	<Frame name="BibActionButton77CooldownCountFrame" parent="BibActionButton77" hidden="true">
        <Size>
            <AbsDimension x="32" y="32"/>
        </Size>
        <Anchors>
            <Anchor point="CENTER" relativeTo="$parent" relativePoint="CENTER">
                <Offset>
                    <AbsDimension x="0" y="0"/>
                </Offset>
            </Anchor>
        </Anchors>
		<Layers>
			<Layer level="ARTWORK">
				<FontString name="BibActionButton77CooldownCount" inherits="GameFontNormalLarge" hidden="true" justifyH="CENTER">
					<Anchors>
						<Anchor point="CENTER">
							<Offset>
								<AbsDimension x="0" y="0"/>
							</Offset>
						</Anchor>
					</Anchors>
				</FontString>
			</Layer>
		</Layers>
	</Frame>
	<Frame name="BibActionButton78CooldownCountFrame" parent="BibActionButton78" hidden="true">
        <Size>
            <AbsDimension x="32" y="32"/>
        </Size>
        <Anchors>
            <Anchor point="CENTER" relativeTo="$parent" relativePoint="CENTER">
                <Offset>
                    <AbsDimension x="0" y="0"/>
                </Offset>
            </Anchor>
        </Anchors>
		<Layers>
			<Layer level="ARTWORK">
				<FontString name="BibActionButton78CooldownCount" inherits="GameFontNormalLarge" hidden="true" justifyH="CENTER">
					<Anchors>
						<Anchor point="CENTER">
							<Offset>
								<AbsDimension x="0" y="0"/>
							</Offset>
						</Anchor>
					</Anchors>
				</FontString>
			</Layer>
		</Layers>
	</Frame>
	<Frame name="BibActionButton79CooldownCountFrame" parent="BibActionButton79" hidden="true">
        <Size>
            <AbsDimension x="32" y="32"/>
        </Size>
        <Anchors>
            <Anchor point="CENTER" relativeTo="$parent" relativePoint="CENTER">
                <Offset>
                    <AbsDimension x="0" y="0"/>
                </Offset>
            </Anchor>
        </Anchors>
		<Layers>
			<Layer level="ARTWORK">
				<FontString name="BibActionButton79CooldownCount" inherits="GameFontNormalLarge" hidden="true" justifyH="CENTER">
					<Anchors>
						<Anchor point="CENTER">
							<Offset>
								<AbsDimension x="0" y="0"/>
							</Offset>
						</Anchor>
					</Anchors>
				</FontString>
			</Layer>
		</Layers>
	</Frame>
	<Frame name="BibActionButton80CooldownCountFrame" parent="BibActionButton80" hidden="true">
        <Size>
            <AbsDimension x="32" y="32"/>
        </Size>
        <Anchors>
            <Anchor point="CENTER" relativeTo="$parent" relativePoint="CENTER">
                <Offset>
                    <AbsDimension x="0" y="0"/>
                </Offset>
            </Anchor>
        </Anchors>
		<Layers>
			<Layer level="ARTWORK">
				<FontString name="BibActionButton80CooldownCount" inherits="GameFontNormalLarge" hidden="true" justifyH="CENTER">
					<Anchors>
						<Anchor point="CENTER">
							<Offset>
								<AbsDimension x="0" y="0"/>
							</Offset>
						</Anchor>
					</Anchors>
				</FontString>
			</Layer>
		</Layers>
	</Frame>
	<Frame name="BibActionButton81CooldownCountFrame" parent="BibActionButton81" hidden="true">
        <Size>
            <AbsDimension x="32" y="32"/>
        </Size>
        <Anchors>
            <Anchor point="CENTER" relativeTo="$parent" relativePoint="CENTER">
                <Offset>
                    <AbsDimension x="0" y="0"/>
                </Offset>
            </Anchor>
        </Anchors>
		<Layers>
			<Layer level="ARTWORK">
				<FontString name="BibActionButton81CooldownCount" inherits="GameFontNormalLarge" hidden="true" justifyH="CENTER">
					<Anchors>
						<Anchor point="CENTER">
							<Offset>
								<AbsDimension x="0" y="0"/>
							</Offset>
						</Anchor>
					</Anchors>
				</FontString>
			</Layer>
		</Layers>
	</Frame>
	<Frame name="BibActionButton82CooldownCountFrame" parent="BibActionButton82" hidden="true">
        <Size>
            <AbsDimension x="32" y="32"/>
        </Size>
        <Anchors>
            <Anchor point="CENTER" relativeTo="$parent" relativePoint="CENTER">
                <Offset>
                    <AbsDimension x="0" y="0"/>
                </Offset>
            </Anchor>
        </Anchors>
		<Layers>
			<Layer level="ARTWORK">
				<FontString name="BibActionButton82CooldownCount" inherits="GameFontNormalLarge" hidden="true" justifyH="CENTER">
					<Anchors>
						<Anchor point="CENTER">
							<Offset>
								<AbsDimension x="0" y="0"/>
							</Offset>
						</Anchor>
					</Anchors>
				</FontString>
			</Layer>
		</Layers>
	</Frame>
	<Frame name="BibActionButton83CooldownCountFrame" parent="BibActionButton83" hidden="true">
        <Size>
            <AbsDimension x="32" y="32"/>
        </Size>
        <Anchors>
            <Anchor point="CENTER" relativeTo="$parent" relativePoint="CENTER">
                <Offset>
                    <AbsDimension x="0" y="0"/>
                </Offset>
            </Anchor>
        </Anchors>
		<Layers>
			<Layer level="ARTWORK">
				<FontString name="BibActionButton83CooldownCount" inherits="GameFontNormalLarge" hidden="true" justifyH="CENTER">
					<Anchors>
						<Anchor point="CENTER">
							<Offset>
								<AbsDimension x="0" y="0"/>
							</Offset>
						</Anchor>
					</Anchors>
				</FontString>
			</Layer>
		</Layers>
	</Frame>
	<Frame name="BibActionButton84CooldownCountFrame" parent="BibActionButton84" hidden="true">
        <Size>
            <AbsDimension x="32" y="32"/>
        </Size>
        <Anchors>
            <Anchor point="CENTER" relativeTo="$parent" relativePoint="CENTER">
                <Offset>
                    <AbsDimension x="0" y="0"/>
                </Offset>
            </Anchor>
        </Anchors>
		<Layers>
			<Layer level="ARTWORK">
				<FontString name="BibActionButton84CooldownCount" inherits="GameFontNormalLarge" hidden="true" justifyH="CENTER">
					<Anchors>
						<Anchor point="CENTER">
							<Offset>
								<AbsDimension x="0" y="0"/>
							</Offset>
						</Anchor>
					</Anchors>
				</FontString>
			</Layer>
		</Layers>
	</Frame>
	<Frame name="BibActionButton85CooldownCountFrame" parent="BibActionButton85" hidden="true">
        <Size>
            <AbsDimension x="32" y="32"/>
        </Size>
        <Anchors>
            <Anchor point="CENTER" relativeTo="$parent" relativePoint="CENTER">
                <Offset>
                    <AbsDimension x="0" y="0"/>
                </Offset>
            </Anchor>
        </Anchors>
		<Layers>
			<Layer level="ARTWORK">
				<FontString name="BibActionButton85CooldownCount" inherits="GameFontNormalLarge" hidden="true" justifyH="CENTER">
					<Anchors>
						<Anchor point="CENTER">
							<Offset>
								<AbsDimension x="0" y="0"/>
							</Offset>
						</Anchor>
					</Anchors>
				</FontString>
			</Layer>
		</Layers>
	</Frame>
	<Frame name="BibActionButton86CooldownCountFrame" parent="BibActionButton86" hidden="true">
        <Size>
            <AbsDimension x="32" y="32"/>
        </Size>
        <Anchors>
            <Anchor point="CENTER" relativeTo="$parent" relativePoint="CENTER">
                <Offset>
                    <AbsDimension x="0" y="0"/>
                </Offset>
            </Anchor>
        </Anchors>
		<Layers>
			<Layer level="ARTWORK">
				<FontString name="BibActionButton86CooldownCount" inherits="GameFontNormalLarge" hidden="true" justifyH="CENTER">
					<Anchors>
						<Anchor point="CENTER">
							<Offset>
								<AbsDimension x="0" y="0"/>
							</Offset>
						</Anchor>
					</Anchors>
				</FontString>
			</Layer>
		</Layers>
	</Frame>
	<Frame name="BibActionButton87CooldownCountFrame" parent="BibActionButton87" hidden="true">
        <Size>
            <AbsDimension x="32" y="32"/>
        </Size>
        <Anchors>
            <Anchor point="CENTER" relativeTo="$parent" relativePoint="CENTER">
                <Offset>
                    <AbsDimension x="0" y="0"/>
                </Offset>
            </Anchor>
        </Anchors>
		<Layers>
			<Layer level="ARTWORK">
				<FontString name="BibActionButton87CooldownCount" inherits="GameFontNormalLarge" hidden="true" justifyH="CENTER">
					<Anchors>
						<Anchor point="CENTER">
							<Offset>
								<AbsDimension x="0" y="0"/>
							</Offset>
						</Anchor>
					</Anchors>
				</FontString>
			</Layer>
		</Layers>
	</Frame>
	<Frame name="BibActionButton88CooldownCountFrame" parent="BibActionButton88" hidden="true">
        <Size>
            <AbsDimension x="32" y="32"/>
        </Size>
        <Anchors>
            <Anchor point="CENTER" relativeTo="$parent" relativePoint="CENTER">
                <Offset>
                    <AbsDimension x="0" y="0"/>
                </Offset>
            </Anchor>
        </Anchors>
		<Layers>
			<Layer level="ARTWORK">
				<FontString name="BibActionButton88CooldownCount" inherits="GameFontNormalLarge" hidden="true" justifyH="CENTER">
					<Anchors>
						<Anchor point="CENTER">
							<Offset>
								<AbsDimension x="0" y="0"/>
							</Offset>
						</Anchor>
					</Anchors>
				</FontString>
			</Layer>
		</Layers>
	</Frame>
	<Frame name="BibActionButton89CooldownCountFrame" parent="BibActionButton89" hidden="true">
        <Size>
            <AbsDimension x="32" y="32"/>
        </Size>
        <Anchors>
            <Anchor point="CENTER" relativeTo="$parent" relativePoint="CENTER">
                <Offset>
                    <AbsDimension x="0" y="0"/>
                </Offset>
            </Anchor>
        </Anchors>
		<Layers>
			<Layer level="ARTWORK">
				<FontString name="BibActionButton89CooldownCount" inherits="GameFontNormalLarge" hidden="true" justifyH="CENTER">
					<Anchors>
						<Anchor point="CENTER">
							<Offset>
								<AbsDimension x="0" y="0"/>
							</Offset>
						</Anchor>
					</Anchors>
				</FontString>
			</Layer>
		</Layers>
	</Frame>
	<Frame name="BibActionButton90CooldownCountFrame" parent="BibActionButton90" hidden="true">
        <Size>
            <AbsDimension x="32" y="32"/>
        </Size>
        <Anchors>
            <Anchor point="CENTER" relativeTo="$parent" relativePoint="CENTER">
                <Offset>
                    <AbsDimension x="0" y="0"/>
                </Offset>
            </Anchor>
        </Anchors>
		<Layers>
			<Layer level="ARTWORK">
				<FontString name="BibActionButton90CooldownCount" inherits="GameFontNormalLarge" hidden="true" justifyH="CENTER">
					<Anchors>
						<Anchor point="CENTER">
							<Offset>
								<AbsDimension x="0" y="0"/>
							</Offset>
						</Anchor>
					</Anchors>
				</FontString>
			</Layer>
		</Layers>
	</Frame>
	<Frame name="BibActionButton91CooldownCountFrame" parent="BibActionButton91" hidden="true">
        <Size>
            <AbsDimension x="32" y="32"/>
        </Size>
        <Anchors>
            <Anchor point="CENTER" relativeTo="$parent" relativePoint="CENTER">
                <Offset>
                    <AbsDimension x="0" y="0"/>
                </Offset>
            </Anchor>
        </Anchors>
		<Layers>
			<Layer level="ARTWORK">
				<FontString name="BibActionButton91CooldownCount" inherits="GameFontNormalLarge" hidden="true" justifyH="CENTER">
					<Anchors>
						<Anchor point="CENTER">
							<Offset>
								<AbsDimension x="0" y="0"/>
							</Offset>
						</Anchor>
					</Anchors>
				</FontString>
			</Layer>
		</Layers>
	</Frame>
	<Frame name="BibActionButton92CooldownCountFrame" parent="BibActionButton92" hidden="true">
        <Size>
            <AbsDimension x="32" y="32"/>
        </Size>
        <Anchors>
            <Anchor point="CENTER" relativeTo="$parent" relativePoint="CENTER">
                <Offset>
                    <AbsDimension x="0" y="0"/>
                </Offset>
            </Anchor>
        </Anchors>
		<Layers>
			<Layer level="ARTWORK">
				<FontString name="BibActionButton92CooldownCount" inherits="GameFontNormalLarge" hidden="true" justifyH="CENTER">
					<Anchors>
						<Anchor point="CENTER">
							<Offset>
								<AbsDimension x="0" y="0"/>
							</Offset>
						</Anchor>
					</Anchors>
				</FontString>
			</Layer>
		</Layers>
	</Frame>
	<Frame name="BibActionButton93CooldownCountFrame" parent="BibActionButton93" hidden="true">
        <Size>
            <AbsDimension x="32" y="32"/>
        </Size>
        <Anchors>
            <Anchor point="CENTER" relativeTo="$parent" relativePoint="CENTER">
                <Offset>
                    <AbsDimension x="0" y="0"/>
                </Offset>
            </Anchor>
        </Anchors>
		<Layers>
			<Layer level="ARTWORK">
				<FontString name="BibActionButton93CooldownCount" inherits="GameFontNormalLarge" hidden="true" justifyH="CENTER">
					<Anchors>
						<Anchor point="CENTER">
							<Offset>
								<AbsDimension x="0" y="0"/>
							</Offset>
						</Anchor>
					</Anchors>
				</FontString>
			</Layer>
		</Layers>
	</Frame>
	<Frame name="BibActionButton94CooldownCountFrame" parent="BibActionButton94" hidden="true">
        <Size>
            <AbsDimension x="32" y="32"/>
        </Size>
        <Anchors>
            <Anchor point="CENTER" relativeTo="$parent" relativePoint="CENTER">
                <Offset>
                    <AbsDimension x="0" y="0"/>
                </Offset>
            </Anchor>
        </Anchors>
		<Layers>
			<Layer level="ARTWORK">
				<FontString name="BibActionButton94CooldownCount" inherits="GameFontNormalLarge" hidden="true" justifyH="CENTER">
					<Anchors>
						<Anchor point="CENTER">
							<Offset>
								<AbsDimension x="0" y="0"/>
							</Offset>
						</Anchor>
					</Anchors>
				</FontString>
			</Layer>
		</Layers>
	</Frame>
	<Frame name="BibActionButton95CooldownCountFrame" parent="BibActionButton95" hidden="true">
        <Size>
            <AbsDimension x="32" y="32"/>
        </Size>
        <Anchors>
            <Anchor point="CENTER" relativeTo="$parent" relativePoint="CENTER">
                <Offset>
                    <AbsDimension x="0" y="0"/>
                </Offset>
            </Anchor>
        </Anchors>
		<Layers>
			<Layer level="ARTWORK">
				<FontString name="BibActionButton95CooldownCount" inherits="GameFontNormalLarge" hidden="true" justifyH="CENTER">
					<Anchors>
						<Anchor point="CENTER">
							<Offset>
								<AbsDimension x="0" y="0"/>
							</Offset>
						</Anchor>
					</Anchors>
				</FontString>
			</Layer>
		</Layers>
	</Frame>
	<Frame name="BibActionButton96CooldownCountFrame" parent="BibActionButton96" hidden="true">
        <Size>
            <AbsDimension x="32" y="32"/>
        </Size>
        <Anchors>
            <Anchor point="CENTER" relativeTo="$parent" relativePoint="CENTER">
                <Offset>
                    <AbsDimension x="0" y="0"/>
                </Offset>
            </Anchor>
        </Anchors>
		<Layers>
			<Layer level="ARTWORK">
				<FontString name="BibActionButton96CooldownCount" inherits="GameFontNormalLarge" hidden="true" justifyH="CENTER">
					<Anchors>
						<Anchor point="CENTER">
							<Offset>
								<AbsDimension x="0" y="0"/>
							</Offset>
						</Anchor>
					</Anchors>
				</FontString>
			</Layer>
		</Layers>
	</Frame>
</Ui>